{
  "best_checkpoint_path": "D:\\Documentos\\Python Projects\\Avatar-Arcade-Game\\models\\experiment_runs\\20260412_074949\\full_lstm\\checkpoints\\best_lstm.keras",
  "classification_report": "D:\\Documentos\\Python Projects\\Avatar-Arcade-Game\\models\\experiment_runs\\20260412_074949\\full_lstm\\classification_report.txt",
  "confusion_matrix_csv": "D:\\Documentos\\Python Projects\\Avatar-Arcade-Game\\models\\experiment_runs\\20260412_074949\\full_lstm\\confusion_matrix.csv",
  "confusion_matrix_png": "D:\\Documentos\\Python Projects\\Avatar-Arcade-Game\\models\\experiment_runs\\20260412_074949\\full_lstm\\confusion_matrix.png",
  "dataset_shape": [
    459,
    90,
    30
  ],
  "epochs_requested": 100,
  "epochs_run": 15,
  "final_test_accuracy": 0.1304347813129425,
  "final_test_loss": 2.2099263668060303,
  "final_train_accuracy": 0.3146417438983917,
  "final_train_loss": 1.977800726890564,
  "final_val_accuracy": 0.14492753148078918,
  "final_val_loss": 2.209583282470703,
  "history_csv": "D:\\Documentos\\Python Projects\\Avatar-Arcade-Game\\models\\experiment_runs\\20260412_074949\\full_lstm\\training_history.csv",
  "history_png": "D:\\Documentos\\Python Projects\\Avatar-Arcade-Game\\models\\experiment_runs\\20260412_074949\\full_lstm\\training_history.png",
  "model_type": "lstm",
  "predictions_csv": "D:\\Documentos\\Python Projects\\Avatar-Arcade-Game\\models\\experiment_runs\\20260412_074949\\full_lstm\\test_predictions.csv",
  "run_name": "full_lstm",
  "split_copy_paths": {
    "test": "D:\\Documentos\\Python Projects\\Avatar-Arcade-Game\\models\\experiment_runs\\20260412_074949\\full_lstm\\splits\\test_indices.npy",
    "train": "D:\\Documentos\\Python Projects\\Avatar-Arcade-Game\\models\\experiment_runs\\20260412_074949\\full_lstm\\splits\\train_indices.npy",
    "val": "D:\\Documentos\\Python Projects\\Avatar-Arcade-Game\\models\\experiment_runs\\20260412_074949\\full_lstm\\splits\\val_indices.npy"
  },
  "split_label_distribution": {
    "test": {
      "attack_air": 7,
      "attack_earth": 8,
      "attack_fire": 8,
      "attack_water": 8,
      "defense_air": 7,
      "defense_earth": 8,
      "defense_fire": 8,
      "defense_water": 8,
      "idle": 7
    },
    "train": {
      "attack_air": 36,
      "attack_earth": 35,
      "attack_fire": 36,
      "attack_water": 35,
      "defense_air": 36,
      "defense_earth": 36,
      "defense_fire": 35,
      "defense_water": 36,
      "idle": 36
    },
    "val": {
      "attack_air": 8,
      "attack_earth": 8,
      "attack_fire": 7,
      "attack_water": 8,
      "defense_air": 8,
      "defense_earth": 7,
      "defense_fire": 8,
      "defense_water": 7,
      "idle": 8
    }
  },
  "split_sizes": {
    "test": 69,
    "train": 321,
    "val": 69
  },
  "status": "success",
  "tiny_overfit": false
}